tracvote/__init__.py
tracvote/compat.py
tracvote/htdocs/adowngray.png
tracvote/htdocs/adownmod.png
tracvote/htdocs/aupgray.png
tracvote/htdocs/aupmod.png
tracvote/htdocs/css/tracvote.css
tracvote/htdocs/js/tracvote.js
tracvote/locale/de/LC_MESSAGES/tracvote.mo
tracvote/locale/es/LC_MESSAGES/tracvote.mo
tracvote/locale/ko/LC_MESSAGES/tracvote.mo
tracvote/upgrades/__init__.py
tracvote/upgrades/db2.py
TracVote-0.7.0.dist-info/COPYING
TracVote-0.7.0.dist-info/METADATA
TracVote-0.7.0.dist-info/WHEEL
TracVote-0.7.0.dist-info/entry_points.txt
TracVote-0.7.0.dist-info/top_level.txt
TracVote-0.7.0.dist-info/zip-safe
TracVote-0.7.0.dist-info/RECORD
